taficasa_shared_apps/__init__.py
taficasa_shared_apps/after_effects/__init__.py
taficasa_shared_apps/after_effects/middleware.py
taficasa_shared_apps/after_effects/registry.py
taficasa_shared_apps/after_effects/serializers.py
taficasa_shared_apps/after_effects/tasks.py
taficasa_shared_apps/after_effects/tests.py
taficasa_shared_apps/after_effects/urls.py
taficasa_shared_apps/after_effects/views.py
taficasa_shared_apps/cloud_scheduler/__init__.py
taficasa_shared_apps/cloud_scheduler/services.py
taficasa_shared_apps/cloud_scheduler/status.py
taficasa_shared_apps/cloud_scheduler/urls.py
taficasa_shared_apps/cloud_scheduler/views.py
taficasa_shared_apps/core/__init__.py
taficasa_shared_apps/core/auth.py
taficasa_shared_apps/core/constants.py
taficasa_shared_apps/core/currency.py
taficasa_shared_apps/core/datetime.py
taficasa_shared_apps/core/decorators.py
taficasa_shared_apps/core/generators.py
taficasa_shared_apps/core/geography.py
taficasa_shared_apps/core/images.py
taficasa_shared_apps/core/mixins.py
taficasa_shared_apps/core/routers.py
taficasa_shared_apps/core/serializers.py
taficasa_shared_apps/core/transform.py
taficasa_shared_apps/core/urls.py
taficasa_shared_apps/core/checks/__init__.py
taficasa_shared_apps/core/checks/models.py
taficasa_shared_apps/core/checks/permissions.py
taficasa_shared_apps/core/data/__init__.py
taficasa_shared_apps/core/data/products.py
taficasa_shared_apps/core/data/gen/__init__.py
taficasa_shared_apps/core/data/gen/basic.py
taficasa_shared_apps/core/data/gen/demo.py
taficasa_shared_apps/core/data/gen/organizations.py
taficasa_shared_apps/core/data/gen/product_receipts.py
taficasa_shared_apps/core/email/__init__.py
taficasa_shared_apps/core/email/client.py
taficasa_shared_apps/core/email/schema.py
taficasa_shared_apps/core/exceptions/__init__.py
taficasa_shared_apps/core/exceptions/exception_classes.py
taficasa_shared_apps/core/exceptions/handlers.py
taficasa_shared_apps/core/middleware/__init__.py
taficasa_shared_apps-0.3.0.dist-info/LICENSE
taficasa_shared_apps-0.3.0.dist-info/METADATA
taficasa_shared_apps-0.3.0.dist-info/WHEEL
taficasa_shared_apps-0.3.0.dist-info/top_level.txt
taficasa_shared_apps-0.3.0.dist-info/RECORD
