Metadata-Version: 2.1
Name: taficasa-shared-apps
Version: 0.3.0
Summary: This package contains folders and apps needed within TafiCasa apps
Author: Excel Okechukwu
Author-email: excel@taficasa.com
License: Custom License
Classifier: Framework :: Django
Classifier: Programming Language :: Python :: 3
Requires-Python: >=3.8
License-File: LICENSE
Requires-Dist: Django (==4.2.2)
Requires-Dist: django-rest-knox (==4.2.0)
Requires-Dist: djangorestframework (==3.14.0)
Requires-Dist: google-cloud-tasks (==2.16.3)
Requires-Dist: google-cloud-scheduler (==2.13.3)
